pypreprocess/__init__.py
pypreprocess/preprocess.py
pypreprocess/preprocessresponse.py
pypreprocess-1.6.dist-info/LICENSE
pypreprocess-1.6.dist-info/METADATA
pypreprocess-1.6.dist-info/WHEEL
pypreprocess-1.6.dist-info/top_level.txt
pypreprocess-1.6.dist-info/RECORD
