Metadata-Version: 2.1
Name: pypreprocess
Version: 1.6
Summary: Preprocess SDK
Author: Preprocess
Author-email: <support@preprocess.co>
Keywords: python,python3,preprocess,chunks,paragraphs,chunk,paragraph,llama,llamaondex,langchain,chunking,llm,rag
Classifier: Development Status :: 4 - Beta
Classifier: Intended Audience :: Developers
Classifier: Programming Language :: Python :: 3
Classifier: Operating System :: Unix
Classifier: Operating System :: MacOS :: MacOS X
Classifier: Operating System :: Microsoft :: Windows
Classifier: License :: OSI Approved :: MIT License
License-File: LICENSE
Requires-Dist: requests
